{"cameraMode":{"drawMode":0,"name":"Shaded","section":"Shading Mode"},"sceneLighting":true,"audioPlay":false,"sceneViewState":{"showFog":true,"showMaterialUpdate":false,"showSkybox":true,"showFlares":true,"showImageEffects":true,"showParticleSystems":true},"in2DMode":false,"pivot":{"x":14.582408905029297,"y":6.904243469238281,"z":-19.415401458740236},"rotation":{"x":-0.17486847937107087,"y":0.1286725103855133,"z":-0.02305702678859234,"w":-0.9758754372596741},"size":44.663612365722659,"orthographic":false}